{"chunk_definitions":[{"row":9,"row_count":1,"visible":true,"expansion_state":0,"options":{"engine":"r","label":"setup","include":false},"document_id":"313124CE","chunk_id":"csetup_chunk","chunk_label":"setup"},{"row":19,"row_count":1,"visible":true,"expansion_state":0,"options":{"engine":"r","warning":false,"message":false,"label":"unnamed-chunk-78"},"document_id":"C3D35183","chunk_id":"cniqyrmbswki1","chunk_label":"unnamed-chunk-1"},{"row":60,"row_count":1,"visible":true,"expansion_state":0,"options":{"engine":"r","label":"unnamed-chunk-164"},"document_id":"313124CE","chunk_id":"cxtbhvuw5ltpb","chunk_label":"unnamed-chunk-2"},{"row":94,"row_count":1,"visible":true,"expansion_state":0,"options":{"engine":"r","fig.width":7.1,"fig.height":3.54,"label":"unnamed-chunk-176"},"document_id":"313124CE","chunk_id":"cdg9fn3dyt0s3","chunk_label":"unnamed-chunk-3"},{"row":137,"row_count":1,"visible":true,"expansion_state":0,"options":{"engine":"r","label":"unnamed-chunk-173"},"document_id":"424CC8A3","chunk_id":"cg78azcmvkvbu","chunk_label":"unnamed-chunk-5"},{"row":146,"row_count":1,"visible":true,"expansion_state":0,"options":{"engine":"r","label":"unnamed-chunk-179"},"document_id":"424CC8A3","chunk_id":"czquldc0t5wny","chunk_label":"unnamed-chunk-6"},{"row":153,"row_count":1,"visible":true,"expansion_state":0,"options":{"engine":"r","label":"unnamed-chunk-141"},"document_id":"C3D35183","chunk_id":"co690sy351rmc","chunk_label":"unnamed-chunk-7"},{"row":158,"row_count":1,"visible":true,"expansion_state":0,"options":{"engine":"r","label":"unnamed-chunk-177"},"document_id":"424CC8A3","chunk_id":"cqq4fbi68gkpm","chunk_label":"unnamed-chunk-8"}],"doc_write_time":1614565001,"chunk_rendered_width":700}